yamla/metadata.py
yamla-0.0.1.dist-info/METADATA
yamla-0.0.1.dist-info/WHEEL
yamla-0.0.1.dist-info/entry_points.txt
yamla-0.0.1.dist-info/RECORD
