Metadata-Version: 2.4
Name: yamla
Version: 0.0.1
Summary: A YAML Parser and Emitter
Project-URL: Source, https://gitlab.com/ambhora/software/yamla
Author-email: Jayesh Badwaik <j.badwaik@fz-juelich.de>
License-Expression: Apache-2.0
Requires-Dist: livereload
Requires-Dist: pyyaml
Requires-Dist: ruamel-yaml>=0.18
Requires-Dist: semver
